simple_latex_ocr/__init__.py
simple_latex_ocr/get_lastest_model.py
simple_latex_ocr/main.py
simple_latex_ocr/models.py
simple_latex_ocr/utils.py
simple_latex_ocr/utils_load.py
simple_latex_ocr/api/__init__.py
simple_latex_ocr/api/app.py
simple_latex_ocr/api/run.py
simple_latex_ocr/api/streamlit.py
simple_latex_ocr-0.0.9.dist-info/LICENSE
simple_latex_ocr-0.0.9.dist-info/METADATA
simple_latex_ocr-0.0.9.dist-info/WHEEL
simple_latex_ocr-0.0.9.dist-info/entry_points.txt
simple_latex_ocr-0.0.9.dist-info/top_level.txt
simple_latex_ocr-0.0.9.dist-info/RECORD
