Metadata-Version: 2.1
Name: simple-latex-ocr
Version: 0.0.9
Summary: A simple LaTeX OCR package
Home-page: https://github.com/chaodreaming/Simple-LaTeX-OCR
Author: chaodreaming
Author-email: chaodreaming@gmail.com
License: Apache-2.0
Keywords: ocr, image to text, latex
Platform: Any
Classifier: Development Status :: 3 - Alpha
Classifier: Intended Audience :: Developers
Classifier: License :: OSI Approved :: Apache Software License
Classifier: Programming Language :: Python :: 3.8
Classifier: Programming Language :: Python :: 3.9
Classifier: Programming Language :: Python :: 3.10
Classifier: Programming Language :: Python :: 3.11
Requires-Python: >=3.8
License-File: LICENSE
Requires-Dist: onnxruntime-gpu
Requires-Dist: tokenizers >=0.13.2
Requires-Dist: numpy
Requires-Dist: opencv-python
Requires-Dist: Pillow >=9.2.0
Requires-Dist: PyYAML >=6.0.0
Requires-Dist: transformers
Requires-Dist: flask
Requires-Dist: fastapi
Requires-Dist: uvicorn
Requires-Dist: opencv-python-headless
Requires-Dist: easydict >=1.13
Requires-Dist: streamlit
Requires-Dist: python-multipart
Requires-Dist: simple-latex-ocr
